mcp_package_hero/__init__.py
mcp_package_hero/github_client.py
mcp_package_hero/llms_txt_client.py
mcp_package_hero/llms_txt_generator.py
mcp_package_hero/llms_txt_models.py
mcp_package_hero/models.py
mcp_package_hero/raters/__init__.py
mcp_package_hero/raters/dart_rater.py
mcp_package_hero/raters/javascript_rater.py
mcp_package_hero/raters/python_rater.py
mcp_package_hero/raters/rust_rater.py
mcp_package_hero/rating_calculator.py
mcp_package_hero/registries/__init__.py
mcp_package_hero/registries/base.py
mcp_package_hero/registries/crates.py
mcp_package_hero/registries/npm.py
mcp_package_hero/registries/pubdev.py
mcp_package_hero/registries/pypi.py
mcp_package_hero/server.py
mcp_package_hero-1.3.0.dist-info/WHEEL
mcp_package_hero-1.3.0.dist-info/entry_points.txt
mcp_package_hero-1.3.0.dist-info/METADATA
mcp_package_hero-1.3.0.dist-info/RECORD
