Metadata-Version: 2.3
Name: mcp-package-hero
Version: 1.3.0
Summary: MCP server for package version checking, quality rating, and llms.txt documentation across PyPI, npm, pub.dev, and crates.io
Keywords: mcp,package,version,rating,quality,pypi,npm,pub.dev,fastmcp
Author: Ulrich Diedrichsen
Author-email: Ulrich Diedrichsen <uli@moinsen.dev>
License: MIT
Classifier: Development Status :: 5 - Production/Stable
Classifier: Intended Audience :: Developers
Classifier: License :: OSI Approved :: MIT License
Classifier: Programming Language :: Python :: 3
Classifier: Programming Language :: Python :: 3.10
Classifier: Programming Language :: Python :: 3.11
Classifier: Programming Language :: Python :: 3.12
Classifier: Programming Language :: Python :: 3.13
Requires-Dist: fastmcp>=2.12.4
Requires-Dist: httpx>=0.28.1
Requires-Dist: pydantic>=2.11.10
Requires-Python: >=3.10
Project-URL: Documentation, https://github.com/moinsen-dev/mcp-package-hero/blob/main/README.md
Project-URL: Homepage, https://github.com/moinsen-dev/mcp-package-hero
Project-URL: Issues, https://github.com/moinsen-dev/mcp-package-hero/issues
Project-URL: Repository, https://github.com/moinsen-dev/mcp-package-hero
